smpl_logger/__init__.py
smpl_logger/logger.py
smpl_logger-0.1.5.dist-info/licenses/LICENSE
smpl_logger-0.1.5.dist-info/METADATA
smpl_logger-0.1.5.dist-info/WHEEL
smpl_logger-0.1.5.dist-info/top_level.txt
smpl_logger-0.1.5.dist-info/RECORD
