Metadata-Version: 2.4
Name: smpl-logger
Version: 0.1.5
Summary: A simple logging library with colored output and file rotation support
Author-email: greengoblinalex <greengoblinalex@mail.ru>
License-Expression: MIT
Project-URL: Homepage, https://github.com/greengoblinalex/simple-logger
Project-URL: Bug Tracker, https://github.com/greengoblinalex/simple-logger/issues
Project-URL: Source Code, https://github.com/greengoblinalex/simple-logger
Project-URL: Documentation, https://github.com/greengoblinalex/simple-logger#readme
Keywords: logging,logger,colored,rotation,python
Classifier: Development Status :: 4 - Beta
Classifier: Intended Audience :: Developers
Classifier: Operating System :: OS Independent
Classifier: Programming Language :: Python :: 3
Classifier: Programming Language :: Python :: 3.6
Classifier: Programming Language :: Python :: 3.7
Classifier: Programming Language :: Python :: 3.8
Classifier: Programming Language :: Python :: 3.9
Classifier: Programming Language :: Python :: 3.10
Classifier: Programming Language :: Python :: 3.11
Classifier: Programming Language :: Python :: 3.12
Classifier: Topic :: Software Development :: Libraries :: Python Modules
Classifier: Topic :: System :: Logging
Requires-Python: >=3.6
License-File: LICENSE
Dynamic: license-file
